{
  "raceTitle": "Insurance Commissioner - Statewide Results",
  "Reporting": "99.7% (25,501 of 25,585) precincts reporting",
  "ReportingTime": "October 19, 2022, 1:23 p.m.",
  "candidates": [
    {
      "Name": "Ricardo Lara",
      "Party": "Dem",
      "Votes": "5,371,468",
      "Percent": "73.2",
      "incumbent": true
    },
    {
      "Name": "Robert Howell",
      "Party": "Rep",
      "Votes": "1,969,401",
      "Percent": "26.8",
      "incumbent": false
    }
  ],
  "slug": "insurance-commissioner",
  "url": "https://api.sos.ca.gov/returns/insurance-commissioner",
  "scraped_datetime": "2022-10-19T13:43:31.429859-07:00"
}
