{
  "Reporting": "0.0% (0 of 25,603) precincts reporting",
  "ReportingTime": "October 31, 2022, 2:42 p.m.",
  "raceTitle": "Supreme Court Justice - Statewide Results",
  "scraped_datetime": "2022-11-01T13:53:31.770639-07:00",
  "slug": "supreme-court",
  "supreme-court": [
    {
      "Name": "Patricia Guerrero",
      "noPercent": "0.0",
      "noVotes": "0",
      "yesPercent": "0.0",
      "yesVotes": "0"
    },
    {
      "Name": "Martin J. Jenkins",
      "noPercent": "0.0",
      "noVotes": "0",
      "yesPercent": "0.0",
      "yesVotes": "0"
    },
    {
      "Name": "Goodwin Liu",
      "noPercent": "0.0",
      "noVotes": "0",
      "yesPercent": "0.0",
      "yesVotes": "0"
    },
    {
      "Name": "Joshua P. Groban",
      "noPercent": "0.0",
      "noVotes": "0",
      "yesPercent": "0.0",
      "yesVotes": "0"
    }
  ],
  "url": "https://api.sos.ca.gov/returns/supreme-court"
}