{
  "Reporting": "91.4% (23,408 of 25,603) precincts reporting",
  "ReportingTime": "October 21, 2022, 2:03 p.m.",
  "candidates": [
    {
      "Name": "Malia M. Cohen",
      "Party": "Dem",
      "Percent": "71.0",
      "Votes": "2,437,284",
      "incumbent": false
    },
    {
      "Name": "Lanhee J. Chen",
      "Party": "Rep",
      "Percent": "29.0",
      "Votes": "995,964",
      "incumbent": false
    }
  ],
  "raceTitle": "Controller - Statewide Results",
  "scraped_datetime": "2022-10-21T14:45:31.210242-07:00",
  "slug": "controller",
  "url": "https://api.sos.ca.gov/returns/controller"
}